folderless/__init__.py
folderless/admin.py
folderless/apps.py
folderless/conf.py
folderless/fields.py
folderless/forms.py
folderless/inlines.py
folderless/models.py
folderless/utils.py
folderless/locale/README
folderless/locale/de/LC_MESSAGES/django.mo
folderless/locale/de/LC_MESSAGES/django.po
folderless/locale/en/LC_MESSAGES/django.mo
folderless/locale/en/LC_MESSAGES/django.po
folderless/migrations/0001_initial.py
folderless/migrations/0002_auto_20180418_0559.py
folderless/migrations/0003_auto_20200407_0856.py
folderless/migrations/0004_alter_file_type.py
folderless/migrations/__init__.py
folderless/static/folderless/css/folderless.css
folderless/static/folderless/js/jquery.folderless_change_list.js
folderless/static/folderless/js/jquery.folderless_file_widget.js
folderless/static/folderless/js/jquery.folderless_widget_init.js
folderless/static/folderless/js/jquery_post_init.js
folderless/static/folderless/js/jquery_pre_init.js
folderless/static/folderless/js/popup_handling.js
folderless/static/folderless/js/vendor/jquery.fileupload.js
folderless/static/folderless/js/vendor/jquery.iframe-transport.js
folderless/static/folderless/js/vendor/jquery.ui.widget.js
folderless/static/folderless/js-legacy/jquery.folderless_change_list.js
folderless/static/folderless/js-legacy/jquery.folderless_file_widget.js
folderless/static/folderless/js-legacy/jquery.folderless_widget_init.js
folderless/static/folderless/js-legacy/jquery_post_init.js
folderless/static/folderless/js-legacy/jquery_pre_init.js
folderless/static/folderless/js-legacy/popup_handling.js
folderless/static/folderless/js-legacy/vendor/jquery-1.9.1.min.js
folderless/static/folderless/js-legacy/vendor/jquery.fileupload.js
folderless/static/folderless/js-legacy/vendor/jquery.iframe-transport.js
folderless/static/folderless/js-legacy/vendor/jquery.ui.widget.js
folderless/templates/admin/folderless/file_widget.html
folderless/templates/admin/folderless/file/change_list.html
folderless/templatetags/__init__.py
django_folderless-0.5.0.dist-info/LICENSE
django_folderless-0.5.0.dist-info/METADATA
django_folderless-0.5.0.dist-info/WHEEL
django_folderless-0.5.0.dist-info/top_level.txt
django_folderless-0.5.0.dist-info/RECORD
