Metadata-Version: 2.1
Name: django-folderless
Version: 0.5.0
Summary: folderless media management for django
Home-page: http://github.com/benzkji/django-folderless
Author: Ben Stähli
Author-email: bnzk@bnzk.ch
License: BSD
Platform: OS Independent
Classifier: Development Status :: 4 - Beta
Classifier: Framework :: Django
Classifier: Intended Audience :: Developers
Classifier: License :: OSI Approved :: BSD License
Classifier: Operating System :: OS Independent
Classifier: Programming Language :: Python
Classifier: Topic :: Internet :: WWW/HTTP
License-File: LICENSE
Requires-Dist: Django (>=1.8)
Requires-Dist: easy-thumbnails (>=2.0)
Requires-Dist: django-appconf (>=0.6)
